{
  "id": "crawled-276106",
  "title": "[NX 스튜디오] [Project TAL] TA 모집 (경력)",
  "company": "㈜매드엔진",
  "jobField": "게임개발(클라이언트), 인터페이스 디자인, 원화, 모델링, 이펙트·FX",
  "keywords": "클라이언트, Python, 인터페이스, AD, TA, 아트, 테크니컬아트",
  "mainGame": "나이트 크로우",
  "gameCategory": "온라인PC게임, 콘솔게임 RPG",
  "experience": "경력 3년 이상",
  "employmentType": "정규직",
  "education": "학력무관",
  "position": "사원, 주임/계장, 대리",
  "recruitCount": "O명",
  "salary": "면접 시 협의\n연봉검색",
  "deadline": "채용시 마감",
  "description": "지원하기\n\n[지원자격]\n\n- TA 외 게임 아트 경력 3년 이상 및 TA경력 3년 이상\n\n- 원활한 의사소통과 협업에 대한 이해도 보유\n\n- 문제 해결에 대한 책임감 있는 태도\n\n- 언리얼 엔진에 대한 전반적인 경험 및 지식 보유\n\n- Houdini, Blender 등 DCC 툴 활용 능력\n\n\n\n[우대사항]\n\n- 머티리얼 제작 역량 및 최적화 경험\n\n- 아트 리소스 제작 워크플로우에 대한 이해\n\n-  메타휴먼 활용 경험 및 애니메이션 제작 경험\n\n - 게임 엔진 기능 및 렌더 파이프라인에 대한 이해\n\n - 새로운 플러그인 및 툴에 대한 탐구 의지\n\n - 언리얼 엔진 기반 MMORPG 또는 콘솔 프로젝트 오픈 경험\n\n - AI 활용한 리소스 제작 경험\n\n - C++ 기반 개발 경험",
  "updatedAt": "2026-04-03",
  "link": "https://www.gamejob.co.kr/Recruit/GI_Read/View?GI_No=276106",
  "source": "GameJob"
}