{
  "id": "crawled-276959",
  "title": "[프로젝트O] 퀘스트 및 설정 기획자 모집",
  "company": "라이온하트스튜디오",
  "jobField": "게임기획",
  "keywords": "게임기획, 퀘스트",
  "mainGame": "오딘: 발할라 라이징",
  "gameCategory": "온라인PC게임, 모바일게임 RPG, Shooting",
  "experience": "경력 3년 이상",
  "employmentType": "정규직",
  "education": "학력무관",
  "position": "주임/계장, 대리, 과장",
  "recruitCount": "O명",
  "salary": "회사내규에 따름 / 면접 시 협의\n연봉검색",
  "deadline": "채용시 마감",
  "description": "[담당업무]\n- 메인 및 서브 퀘스트 기획 및 플로우 설계\n- 설정과 플레이 동선을 연결하는 콘텐츠 설계\n- 기존 세계관 및 메인 스토리를 기반으로 한 지역·세력·인물 설정 확장\n- 지역 단위 스토리라인 및 에피소드 구성\n- NPC 개별 서사 및 관계 구조 설계\n\n[지원자격]\n- 퀘스트 또는 설정 기획 경력 3년 이상인 분\n- 메인/서브 퀘스트 플로우 설계 및 기획 경험이 있는 분\n- 기존 세계관을 기반으로 지역/에피소드 단위 서사 확장 경험이 있는 분\n- 유관 부서와의 협업 경험 및 커뮤니케이션 역량이 있는 분\n- 게임의 설정과 전달에 대해 다양하게 고민하고 시도할 열정과 의지가 가득하신 분\n\n[우대사항]\n- MMORPG 개발 경력이 있는 분\n- Unreal 기반 퀘스트 툴 사용 경험이 있는 분\n- 북유럽 신화 및 배경에 대한 이해가 있는 분\n- 원전을 그대로 옮기기보다, 세계관의 톤에 맞게 재해석할 수 있는 분\n- MMORPG 장르 게임의 심도 있는 플레이 경험이 있는 분",
  "updatedAt": "2026-04-03",
  "link": "https://www.gamejob.co.kr/Recruit/GI_Read/View?GI_No=276959",
  "source": "GameJob"
}