{
  "id": "crawled-275851",
  "title": "[디나미스원] 프로젝트 AT 시스템 기획자 모집",
  "company": "디나미스원㈜",
  "jobField": "게임개발(모바일), 게임기획",
  "keywords": "모바일, 게임기획, 시스템기획, 컨텐츠, 유료화, UI·UX, 서브컬쳐, 서브컬처",
  "mainGame": "-",
  "gameCategory": "모바일게임 RPG",
  "experience": "무관",
  "employmentType": "정규직",
  "education": "학력무관",
  "position": "사원",
  "recruitCount": "O명",
  "salary": "회사내규에 따름\n연봉검색",
  "deadline": "채용시 마감",
  "description": "[담당업무]\n   - 게임 내 메타 시스템 및 데이터 구조 설계\n   - 컨텐츠 UI/UX 설계\n\n[지원자격]\n   - 아이디어를 논리적으로 제시하고 간결하게 문서화 가능하신 분\n   - 능동적, 자기 주도적으로 업무 진행이 가능하신 분\n   - 타 부서와 커뮤니케이션이 원활하신 분\n\n[우대사항]\n   - Unity 기반의 프로젝트 경험\n   - 3년 이상의 유관 경력 보유\n   - 최신 게임 트렌드에 밝으신 분\n   - 하나의 게임을 심도 있게 플레이하신 분\n   - 서브컬쳐에 대한 관심과 이해도가 높으신 분\n\n[복리후생]\n   - 비포괄 임금제\n   - 선택적 근로시간제\n   - 중석식대, 복지 포인트, 건강 검진(본인 외 최대2인),허먼밀러 및 최고사양 장비, \n      각종 경조사 지원 등\n\n   ※ 지원 서류 중 허위 사실이 있을 경우 불합격 혹은 입사가 취소될 수 있습니다.\n   ※ 법령에 따라 국가보훈대상자 및 장애인 등 취업 보호 대상자를 우대합니다.",
  "updatedAt": "2026-04-03",
  "link": "https://www.gamejob.co.kr/Recruit/GI_Read/View?GI_No=275851",
  "source": "GameJob"
}