{
  "id": "276767",
  "title": "[쿠키런 킹덤] 스토리 아티스트",
  "company": "데브시스터즈㈜",
  "link": "https://www.gamejob.co.kr/Recruit/GI_Read/View?GI_No=276767",
  "careerFromList": "",
  "jobField": "게임기획",
  "keywords": "시나리오, 콘텐츠, 스토리기획, 스토리텔링, 내러티브",
  "mainGame": "[쿠키런: 오븐브레이크], [쿠키런: 킹덤], [쿠키런: 모험의탑], [쿠키런 클래식]",
  "gameCategory": "모바일게임 RPG, Casual",
  "experience": "경력 3년 이상",
  "employmentType": "정규직",
  "education": "학력무관",
  "position": "사원, 대리",
  "recruitCount": "O명",
  "salary": "면접 시 협의\n연봉검색",
  "deadline": "채용시 마감",
  "realDescription": "상세 내용을 가져올 수 없습니다."
}